MANIFEST.in
README.md
setup.py
migranto/__init__.py
migranto.egg-info/PKG-INFO
migranto.egg-info/SOURCES.txt
migranto.egg-info/dependency_links.txt
migranto.egg-info/entry_points.txt
migranto.egg-info/not-zip-safe
migranto.egg-info/requires.txt
migranto.egg-info/top_level.txt
migranto/lib/__init__.py
migranto/lib/db.py
migranto/lib/error.py
migranto/lib/main.py
migranto/lib/printer.py
migranto/lib/sql.py
migranto/lib/utils.py