Metadata-Version: 1.0
Name: migranto
Version: 0.1.9
Summary: Simple SQL migration tool for SQLite and PostgreSQL
Home-page: https://github.com/velocityzen/migranto
Author: Alexey Novikov
Author-email: velocityzen@gmail.com
License: BSD
Platform: UNKNOWN
